maib_ecommerce_sdk/__init__.py
maib_ecommerce_sdk/maib_api.py
maib_ecommerce_sdk/maib_auth.py
maib_ecommerce_sdk/maib_sdk.py
maib_ecommerce_sdk-1.1.4.dist-info/licenses/LICENSE
maib_ecommerce_sdk-1.1.4.dist-info/METADATA
maib_ecommerce_sdk-1.1.4.dist-info/WHEEL
maib_ecommerce_sdk-1.1.4.dist-info/top_level.txt
maib_ecommerce_sdk-1.1.4.dist-info/RECORD
