Metadata-Version: 2.4
Name: maib-ecommerce-sdk
Version: 1.1.4
Summary: Python SDK for maib ecommerce API
Author: Alexander Minza
License-Expression: GPL-3.0-or-later
Project-URL: Homepage, https://github.com/alexminza/maib-ecommerce-sdk-python
Project-URL: Issues, https://github.com/alexminza/maib-ecommerce-sdk-python/issues
Project-URL: Repository, https://github.com/alexminza/maib-ecommerce-sdk-python
Project-URL: Documentation, https://docs.maibmerchants.md/e-commerce/
Keywords: maib,moldova,ecommerce,payments,api,sdk,python
Classifier: Intended Audience :: Developers
Classifier: Operating System :: OS Independent
Classifier: Programming Language :: Python :: 3
Classifier: Topic :: Software Development :: Libraries :: Python Modules
Requires-Python: >=3.9
License-File: LICENSE
Requires-Dist: httpx
Dynamic: license-file
